<layouts xmlns:xsi="http://www.w3.org/2001/XMLSchema-instance" xsi:noNamespaceSchemaLocation="https://developer.garmin.com/downloads/connect-iq/resources.xsd">
    <!-- Layouts used for the for the four quadrants. -->
    <layout id="WahooLayout16">
        <drawable class="Background" />
        <drawable id="Grid16" />
        <drawable id="averageUp" />
        <drawable id="averageDown" />
        
        <!-- Big quadrant -->
        <label id="FIELD1" x="98%" y="3%" color="Graphics.COLOR_LT_GRAY" justification="Graphics.TEXT_JUSTIFY_RIGHT" font="@Fonts.Bebas_40" />
        <label id="FIELD1_value" x="90%" y="4%" color="Graphics.COLOR_BLACK" justification="Graphics.TEXT_JUSTIFY_RIGHT" font="@Fonts.Bebas_150" />
        <label id="FIELD1_decimal" x="98%" y="9%" color="Graphics.COLOR_BLACK" justification="Graphics.TEXT_JUSTIFY_RIGHT" font="@Fonts.Bebas_60" />
        
        <!-- 1st Small number quadrant -->
        <label id="FIELD2" x="48%" y="45%" color="Graphics.COLOR_LT_GRAY" justification="Graphics.TEXT_JUSTIFY_RIGHT" font="@Fonts.Bebas_30" />
        <label id="FIELD2_value" x="44%" y="46%" color="Graphics.COLOR_BLACK" justification="Graphics.TEXT_JUSTIFY_RIGHT" font="@Fonts.Bebas_60" />
        <label id="FIELD2_decimal" x="48%" y="48%" color="Graphics.COLOR_BLACK" justification="Graphics.TEXT_JUSTIFY_RIGHT" font="@Fonts.Bebas_30" />
        
        <!-- 2nd Small number quadrant -->
        <label id="FIELD3" x="98%" y="45%" color="Graphics.COLOR_LT_GRAY" justification="Graphics.TEXT_JUSTIFY_RIGHT" font="@Fonts.Bebas_30" />
        <label id="FIELD3_value" x="94%" y="46%" color="Graphics.COLOR_BLACK" justification="Graphics.TEXT_JUSTIFY_RIGHT" font="@Fonts.Bebas_60" />
        <label id="FIELD3_decimal" x="98%" y="48%" color="Graphics.COLOR_BLACK" justification="Graphics.TEXT_JUSTIFY_RIGHT" font="@Fonts.Bebas_30" />
        
        <!-- 3rd Small number quadrant -->
        <label id="FIELD4" x="48%" y="65%" color="Graphics.COLOR_LT_GRAY" justification="Graphics.TEXT_JUSTIFY_RIGHT" font="@Fonts.Bebas_30" />
        <label id="FIELD4_value" x="44%" y="66%" color="Graphics.COLOR_BLACK" justification="Graphics.TEXT_JUSTIFY_RIGHT" font="@Fonts.Bebas_60" />
        <label id="FIELD4_decimal" x="48%" y="68%" color="Graphics.COLOR_BLACK" justification="Graphics.TEXT_JUSTIFY_RIGHT" font="@Fonts.Bebas_30" />
        
        <!-- 4th Small number quadrant -->
        <label id="FIELD5" x="98%" y="65%" color="Graphics.COLOR_LT_GRAY" justification="Graphics.TEXT_JUSTIFY_RIGHT" font="@Fonts.Bebas_30" />
        <label id="FIELD5_value" x="94%" y="66%" color="Graphics.COLOR_BLACK" justification="Graphics.TEXT_JUSTIFY_RIGHT" font="@Fonts.Bebas_60" />
        <label id="FIELD5_decimal" x="98%" y="68%" color="Graphics.COLOR_BLACK" justification="Graphics.TEXT_JUSTIFY_RIGHT" font="@Fonts.Bebas_30" />
        
        <!-- 5th Small number quadrant -->
        <label id="FIELD6" x="48%" y="85%" color="Graphics.COLOR_LT_GRAY" justification="Graphics.TEXT_JUSTIFY_RIGHT" font="@Fonts.Bebas_30" />
        <label id="FIELD6_value" x="44%" y="86%" color="Graphics.COLOR_BLACK" justification="Graphics.TEXT_JUSTIFY_RIGHT" font="@Fonts.Bebas_60" />
        <label id="FIELD6_decimal" x="48%" y="88%" color="Graphics.COLOR_BLACK" justification="Graphics.TEXT_JUSTIFY_RIGHT" font="@Fonts.Bebas_30" />
        
        <!-- 6th Small number quadrant -->
        <label id="FIELD7" x="98%" y="85%" color="Graphics.COLOR_LT_GRAY" justification="Graphics.TEXT_JUSTIFY_RIGHT" font="@Fonts.Bebas_30" />
        <label id="FIELD7_value" x="94%" y="86%" color="Graphics.COLOR_BLACK" justification="Graphics.TEXT_JUSTIFY_RIGHT" font="@Fonts.Bebas_60" />
        <label id="FIELD7_decimal" x="98%" y="88%" color="Graphics.COLOR_BLACK" justification="Graphics.TEXT_JUSTIFY_RIGHT" font="@Fonts.Bebas_30" />
    </layout>

    <layout id="WahooLayout14">
        <drawable class="Background" />
        <drawable id="Grid14" />
        <drawable id="averageUp" />
        <drawable id="averageDown" />

        <!-- Big quadrant -->
        <label id="FIELD1" x="98%" y="3%" color="Graphics.COLOR_LT_GRAY" justification="Graphics.TEXT_JUSTIFY_RIGHT" font="@Fonts.Bebas_60" />
        <label id="FIELD1_value" x="88%" y="7%" color="Graphics.COLOR_BLACK" justification="Graphics.TEXT_JUSTIFY_RIGHT" font="@Fonts.Bebas_180" />
        <label id="FIELD1_decimal" x="98%" y="13%" color="Graphics.COLOR_BLACK" justification="Graphics.TEXT_JUSTIFY_RIGHT" font="@Fonts.Bebas_80" />
        
        <!-- 1st Small number quadrant -->
        <label id="FIELD2" x="48%" y="54%" color="Graphics.COLOR_LT_GRAY" justification="Graphics.TEXT_JUSTIFY_RIGHT" font="@Fonts.Bebas_40" />
        <label id="FIELD2_value" x="43%" y="57%" color="Graphics.COLOR_BLACK" justification="Graphics.TEXT_JUSTIFY_RIGHT" font="@Fonts.Bebas_80" />
        <label id="FIELD2_decimal" x="48%" y="60%" color="Graphics.COLOR_BLACK" justification="Graphics.TEXT_JUSTIFY_RIGHT" font="@Fonts.Bebas_40" />
        
        <!-- 2nd Small number quadrant -->
        <label id="FIELD3" x="98%" y="54%" color="Graphics.COLOR_LT_GRAY" justification="Graphics.TEXT_JUSTIFY_RIGHT" font="@Fonts.Bebas_40" />
        <label id="FIELD3_value" x="93%" y="57%" color="Graphics.COLOR_BLACK" justification="Graphics.TEXT_JUSTIFY_RIGHT" font="@Fonts.Bebas_80" />
        <label id="FIELD3_decimal" x="98%" y="60%" color="Graphics.COLOR_BLACK" justification="Graphics.TEXT_JUSTIFY_RIGHT" font="@Fonts.Bebas_40" />
        
        <!-- 3rd Small number quadrant -->
        <label id="FIELD4" x="48%" y="79%" color="Graphics.COLOR_LT_GRAY" justification="Graphics.TEXT_JUSTIFY_RIGHT" font="@Fonts.Bebas_40" />
        <label id="FIELD4_value" x="43%" y="82%" color="Graphics.COLOR_BLACK" justification="Graphics.TEXT_JUSTIFY_RIGHT" font="@Fonts.Bebas_80" />
        <label id="FIELD4_decimal" x="48%" y="85%" color="Graphics.COLOR_BLACK" justification="Graphics.TEXT_JUSTIFY_RIGHT" font="@Fonts.Bebas_40" />
        
        <!-- 4th Small number quadrant -->
        <label id="FIELD5" x="98%" y="79%" color="Graphics.COLOR_LT_GRAY" justification="Graphics.TEXT_JUSTIFY_RIGHT" font="@Fonts.Bebas_40" />
        <label id="FIELD5_value" x="93%" y="82%" color="Graphics.COLOR_BLACK" justification="Graphics.TEXT_JUSTIFY_RIGHT" font="@Fonts.Bebas_80" />
        <label id="FIELD5_decimal" x="98%" y="85%" color="Graphics.COLOR_BLACK" justification="Graphics.TEXT_JUSTIFY_RIGHT" font="@Fonts.Bebas_40" />
        
    </layout>
</layouts>
